ansible/__init__.py
ansible/__main__.py
ansible/constants.py
ansible/context.py
ansible/keyword_desc.yml
ansible/release.py
ansible/_internal/__init__.py
ansible/_internal/_collection_proxy.py
ansible/_internal/_display_utils.py
ansible/_internal/_event_formatting.py
ansible/_internal/_locking.py
ansible/_internal/_task.py
ansible/_internal/_testing.py
ansible/_internal/_wrapt.py
ansible/_internal/_ansiballz/__init__.py
ansible/_internal/_ansiballz/_builder.py
ansible/_internal/_ansiballz/_wrapper.py
ansible/_internal/_datatag/__init__.py
ansible/_internal/_datatag/_tags.py
ansible/_internal/_datatag/_utils.py
ansible/_internal/_datatag/_wrappers.py
ansible/_internal/_errors/__init__.py
ansible/_internal/_errors/_alarm_timeout.py
ansible/_internal/_errors/_captured.py
ansible/_internal/_errors/_error_factory.py
ansible/_internal/_errors/_error_utils.py
ansible/_internal/_errors/_handler.py
ansible/_internal/_errors/_task_timeout.py
ansible/_internal/_json/__init__.py
ansible/_internal/_json/_legacy_encoder.py
ansible/_internal/_json/_profiles/__init__.py
ansible/_internal/_json/_profiles/_cache_persistence.py
ansible/_internal/_json/_profiles/_inventory_legacy.py
ansible/_internal/_json/_profiles/_legacy.py
ansible/_internal/_plugins/__init__.py
ansible/_internal/_plugins/_cache.py
ansible/_internal/_ssh/__init__.py
ansible/_internal/_ssh/_agent_launch.py
ansible/_internal/_ssh/_ssh_agent.py
ansible/_internal/_templating/__init__.py
ansible/_internal/_templating/_access.py
ansible/_internal/_templating/_chain_templar.py
ansible/_internal/_templating/_datatag.py
ansible/_internal/_templating/_engine.py
ansible/_internal/_templating/_errors.py
ansible/_internal/_templating/_jinja_bits.py
ansible/_internal/_templating/_jinja_common.py
ansible/_internal/_templating/_jinja_patches.py
ansible/_internal/_templating/_jinja_plugins.py
ansible/_internal/_templating/_lazy_containers.py
ansible/_internal/_templating/_marker_behaviors.py
ansible_core-2.19.6.dist-info/licenses/COPYING
ansible_core-2.19.6.dist-info/licenses/licenses/Apache-License.txt
ansible_core-2.19.6.dist-info/licenses/licenses/BSD-3-Clause.txt
ansible_core-2.19.6.dist-info/licenses/licenses/MIT-license.txt
ansible_core-2.19.6.dist-info/licenses/licenses/PSF-license.txt
ansible_core-2.19.6.dist-info/licenses/licenses/simplified_bsd.txt
ansible_core-2.19.6.dist-info/METADATA
ansible_core-2.19.6.dist-info/WHEEL
ansible_core-2.19.6.dist-info/entry_points.txt
ansible_core-2.19.6.dist-info/top_level.txt
ansible_core-2.19.6.dist-info/RECORD
