Metadata-Version: 2.4
Name: ansible-core
Version: 2.19.6
Summary: Radically simple IT automation
Author: Ansible Project
Project-URL: Homepage, https://ansible.com/
Project-URL: Source Code, https://github.com/ansible/ansible/
Project-URL: Bug Tracker, https://github.com/ansible/ansible/issues/
Project-URL: CI: Azure Pipelines, https://dev.azure.com/ansible/ansible/
Project-URL: Documentation, https://docs.ansible.com/ansible-core/
Project-URL: Code of Conduct, https://docs.ansible.com/ansible/latest/community/code_of_conduct.html
Classifier: Development Status :: 5 - Production/Stable
Classifier: Environment :: Console
Classifier: Intended Audience :: Developers
Classifier: Intended Audience :: Information Technology
Classifier: Intended Audience :: System Administrators
Classifier: License :: OSI Approved :: GNU General Public License v3 or later (GPLv3+)
Classifier: Natural Language :: English
Classifier: Operating System :: POSIX
Classifier: Programming Language :: Python :: 3
Classifier: Programming Language :: Python :: 3.11
Classifier: Programming Language :: Python :: 3.12
Classifier: Programming Language :: Python :: 3.13
Classifier: Programming Language :: Python :: 3 :: Only
Classifier: Topic :: System :: Installation/Setup
Classifier: Topic :: System :: Systems Administration
Classifier: Topic :: Utilities
Requires-Python: >=3.11
License-File: COPYING
License-File: licenses/Apache-License.txt
License-File: licenses/BSD-3-Clause.txt
License-File: licenses/MIT-license.txt
License-File: licenses/PSF-license.txt
License-File: licenses/simplified_bsd.txt
Requires-Dist: jinja2>=3.1.0
Requires-Dist: PyYAML>=5.1
Requires-Dist: cryptography
Requires-Dist: packaging
Requires-Dist: resolvelib<2.0.0,>=0.5.3
Dynamic: license-file
